half_adder/half_adder.vhd

--| Libraries |-------------------------------------------------------

library ieee;
use ieee.std_logic_1164.all;

--| Half Adder |------------------------------------------------------

entity half_adder is

    port(
        a, b  : in  std_logic;
        sum   : out std_logic;
        carry : out std_logic
    );

end half_adder;

--| Architecture |----------------------------------------------------

architecture main of half_adder is
begin 

    sum <= a xor b;
    carry <= a and b;

end architecture main;

full_adder/full_adder.vhd

-- Descrição de Hardware (VHDL) de um HALF_ADDER
--
--            ____				
--      a >--|    |--> sum      a | b | c_in | s | c_out 
--           | FA |            --------------------------
--      b >--|____|--> carry    0 | 0 |  0   | 0 |   0
--                              0 | 0 |  1   | 1 |   0
--                              0 | 1 |  0   | 1 |   0
--                              0 | 1 |  1   | 0 |   1
--                              1 | 0 |  0   | 1 |   0
--                              1 | 0 |  1   | 0 |   1
--                              1 | 1 |  0   | 0 |   1
--                              1 | 1 |  1   | 1 |   1
--                             --------------------------
--
-- AUTOR: André Solano F. R. Maiolini
-- DATA: 22/06/2024

library ieee;
use ieee.std_logic_1164.all;

entity full_adder is

    port (
        a, b           : in std_logic;
        carry_in       : in std_logic;
        sum, carry_out : out std_logic
    );

end full_adder;

architecture main of full_adder is 

    -- Sinais internos:

    signal x, y, z : std_logic;

    -- Componentes internos:

    component half_adder is

        port(
            a, b  : in  std_logic;
            sum   : out std_logic;
            carry : out std_logic
        );

    end component half_adder;

begin

        -- Instaciação nominal
        half_adder_1: half_adder port map (
            a     => a,
            b     => b,
            sum   => x,
            carry => y
        );

        -- Instanciação posicional
        half_adder_2: half_adder port map (
            x, carry_in, sum, z
        );

        -- Lógica
        carry_out <= y or z;

end architecture main;

full_adder/full_adder_tb.vhd

-- Arquivo de testes (testbench) para o Full Adder

--| Libraries |-----------------------------------

library ieee;
use ieee.std_logic_1164.all;

--| Entidade |------------------------------------

entity full_adder_tb is
end entity full_adder_tb;

--| Lógica - Testbench |--------------------------

architecture teste of full_adder_tb is
  
  signal a         : std_logic;
  signal b         : std_logic;
  signal carry_in  : std_logic;
  signal sum       : std_logic;
  signal carry_out : std_logic;

  component full_adder is
    port(
      a, b      : in  std_logic;
      carry_in  : in std_logic;
      sum       : out std_logic;
      carry_out : out std_logic
    );
  end component full_adder;

begin
  
  X: full_adder port map (
    a, b, carry_in, sum, carry_out
  ); 

  process
  begin
    a <= 'X';
    b <= 'X';
    carry_in <= 'X';
    wait for 1 ns;

    a <= '0';
    b <= '0';
    carry_in <= '0';
    wait for 1 ns;

    a <= '0';
    b <= '0';
    carry_in <= '1';
    wait for 1 ns;

    a <= '0';
    b <= '1';
    carry_in <= '0';
    wait for 1 ns;

    a <= '0';
    b <= '1';
    carry_in <= '1';
    wait for 1 ns;

    a <= '1';
    b <= '0';
    carry_in <= '0';
    wait for 1 ns;

    a <= '1';
    b <= '0';
    carry_in <= '1';
    wait for 1 ns;

    a <= '1';
    b <= '1';
    carry_in <= '0';
    wait for 1 ns;

    a <= '1';
    b <= '1';
    carry_in <= '1';
    wait for 1 ns;

    wait;

  end process;

end architecture teste;

full_adder/output/full_adder_tb.vcd
$date
  Sat Jun 22 19:42:34 2024
$end
$version
  GHDL v0
$end
$timescale
  1 fs
$end
$scope module standard $end
$upscope $end
$scope module textio $end
$upscope $end
$scope module std_logic_1164 $end
$upscope $end
$scope module full_adder_tb $end
$var reg 1 ! a $end
$var reg 1 " b $end
$var reg 1 # carry_in $end
$var reg 1 $ sum $end
$var reg 1 % carry_out $end
$scope module x $end
$var reg 1 & a $end
$var reg 1 ' b $end
$var reg 1 ( carry_in $end
$var reg 1 ) sum $end
$var reg 1 * carry_out $end
$var reg 1 + x $end
$var reg 1 , y $end
$var reg 1 - z $end
$scope module half_adder_1 $end
$var reg 1 . a $end
$var reg 1 / b $end
$var reg 1 0 sum $end
$var reg 1 1 carry $end
$upscope $end
$scope module half_adder_2 $end
$var reg 1 2 a $end
$var reg 1 3 b $end
$var reg 1 4 sum $end
$var reg 1 5 carry $end
$upscope $end
$upscope $end
$upscope $end
$enddefinitions $end
#0
X!
X"
X#
X$
X%
X&
X'
X(
X)
X*
X+
X,
X-
X.
X/
X0
X1
X2
X3
X4
X5
#1000000
0!
0"
0#
0$
0%
0&
0'
0(
0)
0*
0+
0,
0-
0.
0/
00
01
02
03
04
05
#2000000
1#
1$
1(
1)
13
14
#3000000
1"
0#
1$
1'
0(
1)
1+
1/
10
12
03
14
#4000000
1#
0$
1%
1(
0)
1*
1-
13
04
15
#5000000
1!
0"
0#
1$
0%
1&
0'
0(
1)
0*
0-
1.
0/
03
14
05
#6000000
1#
0$
1%
1(
0)
1*
1-
13
04
15
#7000000
1"
0#
0$
1'
0(
0)
0+
1,
0-
1/
00
11
02
03
04
05
#8000000
1#
1$
1(
1)
13
14
