register_sync_16bit/register_sync_16bit.vhd
-- Descrição de Hardware (VHDL) de um Registrador Síncrono 16 bits c/ CLEAR e PRESET
--
--                  __________
--      not(PR) >--|          |
--      not(CL) >--| register |-->      Q (16 bits)
--      data_in >--|  16 bits |--> not(Q) (16 bits)
--       enable >--|          |
--          CLK >--|__________|
--
--
-- AUTOR: André Solano F. R. Maiolini
-- DATA: 23/06/2024

--| Libraries |--------------------------------------------------------------------------

library ieee;
use ieee.std_logic_1164.all;

--| Buffer |-----------------------------------------------------------------------------

entity register_sync_16bit is
    port (
        data_in   : in  std_logic_vector(15 downto 0);  -- Dados de entrada
        enable    : in  std_logic;                      -- Sinal de habilitação
        PR, CL    : in  std_logic;                      -- Sinais de controle assíncronos 
        CLK       : in  std_logic;                      -- Sinal de clock
        Q, not_Q  : out std_logic_vector(15 downto 0)   -- Dados de saída
    );
end entity register_sync_16bit;

--| Lógica |------------------------------------------------------------------------------

architecture main of register_sync_16bit is

    signal q_reg : std_logic_vector(15 downto 0);

begin

    process (CLK, PR, CL)
    begin
        if PR = '0' then
            q_reg <= x"FFFF";
        elsif CL = '0' then
            q_reg <= x"0000";
        elsif falling_edge(CLK) then
            if enable = '1' then
                q_reg <= data_in;
            end if;
        end if;
    end process;

    Q <= q_reg;
    not_Q <= not(q_reg);

end architecture main;

register_sync_16bit/register_sync_16bit_tb.vhd

-- Arquivo de testes (testbench) para o Registrador 16 bits

--| Libraries |------------------------------------------

library ieee;
use ieee.std_logic_1164.all;

--| Entidade |-------------------------------------------

entity register_sync_16bit_tb is
end entity register_sync_16bit_tb;

--| Lógica - Testbench |---------------------------------

architecture teste of register_sync_16bit_tb is
  
  signal data_in  : std_logic_vector(15 downto 0);
  signal enable   : std_logic;
  signal PR, CL   : std_logic;
  signal Q, not_Q : std_logic_vector(15 downto 0);
  signal CLK      : std_logic := '0';

  component register_sync_16bit is
    port (
        data_in   : in  std_logic_vector(15 downto 0);  -- Dados de entrada
        enable    : in  std_logic;                      -- Sinal de habilitação
        PR, CL    : in  std_logic;                      -- Sinais de controle assíncronos 
        CLK       : in  std_logic;                      -- Sinal de clock
        Q, not_Q  : out std_logic_vector(15 downto 0)   -- Dados de saída
    );
  end component register_sync_16bit;

begin

    REG: register_sync_16bit port map (
        data_in, enable, PR, CL, CLK, Q, not_Q
    );
  
    -- Gerador de clock
    clk_process: process
    begin
        while now < 15 ns loop
            clk <= '0';
            wait for 2 ns;
            clk <= '1';
            wait for 2 ns;
        end loop;
        wait;
    end process clk_process;

    process
    begin

        -- Definindo entradas de controle assíncronas
        PR <= '1';
        CL <= '1';

        -- Test 1: enable = 0
        enable <= '0';
        data_in <= x"AAAA";
        wait for 3 ns;
        
        -- Test 2: enable = 1
        enable <= '1';
        data_in <= x"1234";
        wait for 3 ns;
        
        -- Test 3: enable = 1
        data_in <= x"5678";
        wait for 3 ns;
        
        -- Test 4: enable = 0
        enable <= '0';
        data_in <= x"9ABC";
        wait for 3 ns;

        -- Test 5: enable = 1 (PR)
        enable <= '0';
        PR <= '0';
        data_in <= x"9ABC";
        wait for 3 ns;
        PR <= '1';

        -- Test 6: enable = 1 (CL)
        enable <= '0';
        CL <= '0';
        data_in <= x"9ABC";
        wait for 3 ns;
        CL <= '1';

        wait;

    end process;

end architecture teste;

register_sync_16bit/output/register_sync_16bit_tb.vcd
$date
  Sun Jun 23 02:59:28 2024
$end
$version
  GHDL v0
$end
$timescale
  1 fs
$end
$scope module standard $end
$upscope $end
$scope module textio $end
$upscope $end
$scope module std_logic_1164 $end
$upscope $end
$scope module register_sync_16bit_tb $end
$var reg 16 ! data_in[15:0] $end
$var reg 1 " enable $end
$var reg 1 # pr $end
$var reg 1 $ cl $end
$var reg 16 % q[15:0] $end
$var reg 16 & not_q[15:0] $end
$var reg 1 ' clk $end
$scope module reg $end
$var reg 16 ( data_in[15:0] $end
$var reg 1 ) enable $end
$var reg 1 * pr $end
$var reg 1 + cl $end
$var reg 1 , clk $end
$var reg 16 - q[15:0] $end
$var reg 16 . not_q[15:0] $end
$var reg 16 / q_reg[15:0] $end
$upscope $end
$upscope $end
$enddefinitions $end
#0
b1010101010101010 !
0"
1#
1$
bUUUUUUUUUUUUUUUU %
bUUUUUUUUUUUUUUUU &
0'
b1010101010101010 (
0)
1*
1+
0,
bUUUUUUUUUUUUUUUU -
bUUUUUUUUUUUUUUUU .
bUUUUUUUUUUUUUUUU /
#2000000
1'
1,
#3000000
b0001001000110100 !
1"
b0001001000110100 (
1)
#4000000
b0001001000110100 %
b1110110111001011 &
0'
0,
b0001001000110100 -
b1110110111001011 .
b0001001000110100 /
#6000000
b0101011001111000 !
1'
b0101011001111000 (
1,
#8000000
b0101011001111000 %
b1010100110000111 &
0'
0,
b0101011001111000 -
b1010100110000111 .
b0101011001111000 /
#9000000
b1001101010111100 !
0"
b1001101010111100 (
0)
#10000000
1'
1,
#12000000
0#
b1111111111111111 %
b0000000000000000 &
0'
0*
0,
b1111111111111111 -
b0000000000000000 .
b1111111111111111 /
#14000000
1'
1,
#15000000
1#
0$
b0000000000000000 %
b1111111111111111 &
1*
0+
b0000000000000000 -
b1111111111111111 .
b0000000000000000 /
#16000000
#18000000
1$
1+
