generic_counter/generic_counter.vhd
-- Descrição de Hardware (VHDL) de um Contador Genérico de n bits
--
--                  __________
--          clk >--|          |
--                 | Contador |--> count (n bits) 
--           MR >--|__________|
--
--
-- AUTOR: André Solano F. R. Maiolini
-- DATA: 23/06/2024

--| Libraries |------------------------------------------------------------------------------

library ieee;
use ieee.std_logic_1164.all;
use ieee.numeric_std.all;

--| ALU |------------------------------------------------------------------------------------

entity generic_counter is
    generic(n : integer := 4); -- quantidade de bits do contador
    port (
        clk    : in  std_logic;
        MR     : in  std_logic;
        count  : out std_logic_vector(n - 1 downto 0)
    );
end entity generic_counter;

--| Lógica |----------------------------------------------------------------------------------

architecture main of generic_counter is

    signal count_temp : unsigned(n-1 downto 0);

begin

    contagem : process(clk, MR) 
    begin

        if MR = '0' then

            count_temp <= (others => '0');

        elsif falling_edge(clk) then

            count_temp <= count_temp + 1;

        end if;

    end process contagem;

    count <= std_logic_vector(count_temp);

end architecture main;

generic_counter/generic_counter_tb.vhd

-- Arquivo de testes (testbench) para Contador Genérico

--| Libraries |------------------------------------------

library ieee;
use ieee.std_logic_1164.all;

--| Entidade |-------------------------------------------

entity generic_counter_tb is

    constant n : integer := 4;

end entity generic_counter_tb;

--| Lógica - Testbench |---------------------------------

architecture teste of generic_counter_tb is
  
  signal MR    : std_logic;
  signal clk   : std_logic := '0';
  signal count : std_logic_vector(n-1 downto 0);

begin

    COUNTER: entity work.generic_counter generic map(n) port map (
        clk, MR, count
    );
  
    -- Gerador de clock
    clk_process: process
    begin
        while now < 20 ns loop
            clk <= not clk;
            wait for 2 ns;
        end loop;
        wait;
    end process clk_process;

    -- Master Reset
    master_reset: process
    begin

        MR <= '0';
        wait for 1 ns;
        MR <= '1';
        wait for 14 ns;
        MR <= '0';
        wait for 2 ns;
        MR <= '1';
        wait;

    end process master_reset;

end architecture teste;

generic_counter/output/generic_counter_tb.vcd
$date
  Sun Jun 23 15:40:51 2024
$end
$version
  GHDL v0
$end
$timescale
  1 fs
$end
$scope module standard $end
$upscope $end
$scope module textio $end
$upscope $end
$scope module std_logic_1164 $end
$upscope $end
$scope module numeric_std $end
$upscope $end
$scope module generic_counter_tb $end
$var reg 1 ! mr $end
$var reg 1 " clk $end
$var reg 4 # count[3:0] $end
$scope module counter $end
$var reg 1 $ clk $end
$var reg 1 % mr $end
$var reg 4 & count[3:0] $end
$var reg 4 ' count_temp[3:0] $end
$upscope $end
$upscope $end
$enddefinitions $end
#0
0!
1"
b0000 #
1$
0%
b0000 &
b0000 '
#1000000
1!
1%
#2000000
0"
b0001 #
0$
b0001 &
b0001 '
#4000000
1"
1$
#6000000
0"
b0010 #
0$
b0010 &
b0010 '
#8000000
1"
1$
#10000000
0"
b0011 #
0$
b0011 &
b0011 '
#12000000
1"
1$
#14000000
0"
b0100 #
0$
b0100 &
b0100 '
#15000000
0!
b0000 #
0%
b0000 &
b0000 '
#16000000
1"
1$
#17000000
1!
1%
#18000000
0"
b0001 #
0$
b0001 &
b0001 '
